{
    "manufacturer": "American DJ",
    "name": "X-Scan LED Plus",
    "categories": [
        "Scanner"
    ],
    "meta": {
        "authors": [
            "DjProWings",
            "bwees"
        ],
        "createDate": "2021-01-25",
        "lastModifyDate": "2021-01-25",
        "importPlugin": {
            "plugin": "qlcplus_4.12.1",
            "date": "2021-01-25",
            "comment": "created by Q Light Controller Plus (version 4.12.4 GIT)"
        }
    },
    "wheels": {
        "Colors": {
            "slots": [
                {
                    "type": "Color",
                    "name": "White",
                    "colors": [
                        "#ffffff"
                    ]
                },
                {
                    "type": "Color",
                    "name": "Orange",
                    "colors": [
                        "#ff5500"
                    ]
                },
                {
                    "type": "Color",
                    "name": "Blue",
                    "colors": [
                        "#0000ff"
                    ]
                },
                {
                    "type": "Color",
                    "name": "Green",
                    "colors": [
                        "#00ff00"
                    ]
                },
                {
                    "type": "Color",
                    "name": "Yellow",
                    "colors": [
                        "#ffff00"
                    ]
                },
                {
                    "type": "Color",
                    "name": "Pink",
                    "colors": [
                        "#ff007f"
                    ]
                },
                {
                    "type": "Color",
                    "name": "Light blue",
                    "colors": [
                        "#55aaff"
                    ]
                },
                {
                    "type": "Color",
                    "name": "Light green",
                    "colors": [
                        "#55ff7f"
                    ]
                },
                {
                    "type": "Color",
                    "name": "Light yellow",
                    "colors": [
                        "#ffff7f"
                    ]
                },
                {
                    "type": "Color",
                    "name": "Sound active"
                }
            ]
        },
        "Gobo Wheel": {
            "slots": [
                {
                    "type": "Open"
                },
                {
                    "type": "Gobo",
                    "resource": "gobos/3-fold-swirl",
                    "name": "Gobo 1"
                },
                {
                    "type": "Gobo",
                    "resource": "gobos/biohazard",
                    "name": "Gobo 2"
                },
                {
                    "type": "Gobo",
                    "resource": "gobos/aliases/qlcplus/Chauvet/gobo00040.svg",
                    "name": "Gobo 3"
                },
                {
                    "type": "Gobo",
                    "resource": "gobos/aliases/qlcplus/Chauvet/gobo00008.svg",
                    "name": "Gobo 4"
                },
                {
                    "type": "Gobo",
                    "resource": "gobos/aliases/qlcplus/Chauvet/gobo00009.svg",
                    "name": "Gobo 5"
                },
                {
                    "type": "Gobo",
                    "resource": "gobos/aliases/qlcplus/SGM/gobo00001.svg",
                    "name": "Gobo 6"
                },
                {
                    "type": "Gobo",
                    "resource": "gobos/aliases/qlcplus/SGM/gobo00019.png",
                    "name": "Gobo 7"
                },
                {
                    "type": "Gobo",
                    "resource": "gobos/aliases/qlcplus/ClayPaky/gobo00005.svg",
                    "name": "Gobo 8"
                },
                {
                    "type": "Gobo",
                    "name": "Sound active"
                }
            ]
        }
    },
    "availableChannels": {
        "Pan": {
            "defaultValue": 0,
            "capability": {
                "type": "Pan",
                "angleStart": "0deg",
                "angleEnd": "180deg"
            }
        },
        "Tilt": {
            "defaultValue": 0,
            "capability": {
                "type": "Tilt",
                "angleStart": "0deg",
                "angleEnd": "70deg"
            }
        },
        "Colors": {
            "defaultValue": 0,
            "capabilities": [
                {
                    "dmxRange": [
                        0,
                        14
                    ],
                    "type": "ColorPreset",
                    "comment": "White",
                    "colors": [
                        "#ffffff"
                    ]
                },
                {
                    "dmxRange": [
                        15,
                        29
                    ],
                    "type": "ColorPreset",
                    "comment": "Orange",
                    "colors": [
                        "#ff5500"
                    ]
                },
                {
                    "dmxRange": [
                        30,
                        44
                    ],
                    "type": "ColorPreset",
                    "comment": "Blue",
                    "colors": [
                        "#0000ff"
                    ]
                },
                {
                    "dmxRange": [
                        45,
                        59
                    ],
                    "type": "ColorPreset",
                    "comment": "Green",
                    "colors": [
                        "#00ff00"
                    ]
                },
                {
                    "dmxRange": [
                        60,
                        74
                    ],
                    "type": "ColorPreset",
                    "comment": "Yellow",
                    "colors": [
                        "#ffff00"
                    ]
                },
                {
                    "dmxRange": [
                        75,
                        89
                    ],
                    "type": "ColorPreset",
                    "comment": "Pink",
                    "colors": [
                        "#ff007f"
                    ]
                },
                {
                    "dmxRange": [
                        90,
                        104
                    ],
                    "type": "ColorPreset",
                    "comment": "Light blue",
                    "colors": [
                        "#55aaff"
                    ]
                },
                {
                    "dmxRange": [
                        105,
                        119
                    ],
                    "type": "ColorPreset",
                    "comment": "Light green",
                    "colors": [
                        "#55ff7f"
                    ]
                },
                {
                    "dmxRange": [
                        120,
                        127
                    ],
                    "type": "ColorPreset",
                    "comment": "Light yellow",
                    "colors": [
                        "#ffff7f"
                    ]
                },
                {
                    "dmxRange": [
                        128,
                        254
                    ],
                    "type": "WheelSlot",
                    "slotNumber": 10,
                    "comment": "Rainbow effect slow - fast"
                },
                {
                    "dmxRange": [
                        255,
                        255
                    ],
                    "type": "ColorPreset",
                    "comment": "Sound active"
                }
            ]
        },
        "Gobo Wheel": {
            "defaultValue": 0,
            "capabilities": [
                {
                    "dmxRange": [
                        0,
                        7
                    ],
                    "type": "WheelSlot",
                    "slotNumber": 1,
                    "comment": "Open"
                },
                {
                    "dmxRange": [
                        8,
                        14
                    ],
                    "type": "WheelSlot",
                    "slotNumber": 2,
                    "comment": "Gobo 1"
                },
                {
                    "dmxRange": [
                        15,
                        21
                    ],
                    "type": "WheelSlot",
                    "slotNumber": 3,
                    "comment": "Gobo 2"
                },
                {
                    "dmxRange": [
                        22,
                        28
                    ],
                    "type": "WheelSlot",
                    "slotNumber": 4,
                    "comment": "Gobo 3"
                },
                {
                    "dmxRange": [
                        29,
                        36
                    ],
                    "type": "WheelSlot",
                    "slotNumber": 5,
                    "comment": "Gobo 4"
                },
                {
                    "dmxRange": [
                        37,
                        43
                    ],
                    "type": "WheelSlot",
                    "slotNumber": 6,
                    "comment": "Gobo 5"
                },
                {
                    "dmxRange": [
                        44,
                        50
                    ],
                    "type": "WheelSlot",
                    "slotNumber": 7,
                    "comment": "Gobo 6"
                },
                {
                    "dmxRange": [
                        51,
                        57
                    ],
                    "type": "WheelSlot",
                    "slotNumber": 8,
                    "comment": "Gobo 7"
                },
                {
                    "dmxRange": [
                        58,
                        63
                    ],
                    "type": "WheelSlot",
                    "slotNumber": 9,
                    "comment": "Gobo 8"
                },
                {
                    "dmxRange": [
                        64,
                        71
                    ],
                    "type": "WheelShake",
                    "slotNumber": 10,
                    "comment": "Open shake"
                },
                {
                    "dmxRange": [
                        72,
                        78
                    ],
                    "type": "WheelShake",
                    "slotNumber": 11,
                    "comment": "Gobo 1 shake"
                },
                {
                    "dmxRange": [
                        79,
                        85
                    ],
                    "type": "WheelShake",
                    "slotNumber": 12,
                    "comment": "Gobo 2 shake"
                },
                {
                    "dmxRange": [
                        86,
                        92
                    ],
                    "type": "WheelShake",
                    "slotNumber": 13,
                    "comment": "Gobo 3 shake"
                },
                {
                    "dmxRange": [
                        93,
                        100
                    ],
                    "type": "WheelShake",
                    "slotNumber": 14,
                    "comment": "Gobo 4 shake"
                },
                {
                    "dmxRange": [
                        101,
                        107
                    ],
                    "type": "WheelShake",
                    "slotNumber": 15,
                    "comment": "Gobo 5 shake"
                },
                {
                    "dmxRange": [
                        108,
                        114
                    ],
                    "type": "WheelShake",
                    "slotNumber": 16,
                    "comment": "Gobo 6 shake"
                },
                {
                    "dmxRange": [
                        115,
                        121
                    ],
                    "type": "WheelShake",
                    "slotNumber": 17,
                    "comment": "Gobo 7 shake"
                },
                {
                    "dmxRange": [
                        122,
                        127
                    ],
                    "type": "WheelShake",
                    "slotNumber": 18,
                    "comment": "Gobo 8 shake"
                },
                {
                    "dmxRange": [
                        128,
                        254
                    ],
                    "type": "WheelRotation",
                    "speedStart": "slow CW",
                    "speedEnd": "fast CW",
                    "comment": "Rotation slow to fast"
                },
                {
                    "dmxRange": [
                        255,
                        255
                    ],
                    "type": "WheelSlot",
                    "slotNumber": 20,
                    "comment": "Sound active"
                }
            ]
        },
        "Shutter/Strobe": {
            "defaultValue": 0,
            "capabilities": [
                {
                    "dmxRange": [
                        0,
                        7
                    ],
                    "type": "ShutterStrobe",
                    "shutterEffect": "Closed",
                    "comment": "Blackout"
                },
                {
                    "dmxRange": [
                        8,
                        15
                    ],
                    "type": "ShutterStrobe",
                    "shutterEffect": "Open",
                    "comment": "Shutter open"
                },
                {
                    "dmxRange": [
                        16,
                        131
                    ],
                    "type": "ShutterStrobe",
                    "shutterEffect": "Strobe",
                    "speedStart": "slow",
                    "speedEnd": "fast",
                    "comment": "Strobe slow - fast"
                },
                {
                    "dmxRange": [
                        132,
                        139
                    ],
                    "type": "ShutterStrobe",
                    "shutterEffect": "Open",
                    "comment": "Shutter open"
                },
                {
                    "dmxRange": [
                        140,
                        180
                    ],
                    "type": "ShutterStrobe",
                    "shutterEffect": "Strobe",
                    "comment": "Shutter slow open - fast close",
                    "speedStart": "slow",
                    "speedEnd": "fast",
                    "helpWanted": "Are the automatically added speed values correct?"
                },
                {
                    "dmxRange": [
                        181,
                        189
                    ],
                    "type": "ShutterStrobe",
                    "shutterEffect": "Open",
                    "comment": "Shutter open"
                },
                {
                    "dmxRange": [
                        190,
                        231
                    ],
                    "type": "ShutterStrobe",
                    "shutterEffect": "Strobe",
                    "comment": "Shutter fast open - slow close",
                    "speedStart": "slow",
                    "speedEnd": "fast",
                    "helpWanted": "Are the automatically added speed values correct?"
                },
                {
                    "dmxRange": [
                        232,
                        239
                    ],
                    "type": "ShutterStrobe",
                    "shutterEffect": "Open",
                    "comment": "Shutter open"
                },
                {
                    "dmxRange": [
                        240,
                        247
                    ],
                    "type": "ShutterStrobe",
                    "shutterEffect": "Strobe",
                    "randomTiming": true,
                    "comment": "Random strobe"
                },
                {
                    "dmxRange": [
                        248,
                        255
                    ],
                    "type": "ShutterStrobe",
                    "shutterEffect": "Open",
                    "comment": "Shutter open"
                }
            ]
        },
        "Dimmer": {
            "defaultValue": 0,
            "capability": {
                "type": "Intensity"
            }
        },
        "Moving Head Movement": {
            "defaultValue": 0,
            "capabilities": [
                {
                    "dmxRange": [
                        0,
                        7
                    ],
                    "type": "NoFunction"
                },
                {
                    "dmxRange": [
                        8,
                        28
                    ],
                    "type": "Effect",
                    "effectName": "Movement 1"
                },
                {
                    "dmxRange": [
                        29,
                        49
                    ],
                    "type": "Effect",
                    "effectName": "Movement 2"
                },
                {
                    "dmxRange": [
                        50,
                        70
                    ],
                    "type": "Effect",
                    "effectName": "Movement 3"
                },
                {
                    "dmxRange": [
                        71,
                        91
                    ],
                    "type": "Effect",
                    "effectName": "Movement 4"
                },
                {
                    "dmxRange": [
                        92,
                        112
                    ],
                    "type": "Effect",
                    "effectName": "Movement 5"
                },
                {
                    "dmxRange": [
                        113,
                        133
                    ],
                    "type": "Effect",
                    "effectName": "Movement 6"
                },
                {
                    "dmxRange": [
                        134,
                        154
                    ],
                    "type": "Effect",
                    "effectName": "Movement 7"
                },
                {
                    "dmxRange": [
                        155,
                        175
                    ],
                    "type": "Effect",
                    "effectName": "Movement 8"
                },
                {
                    "dmxRange": [
                        176,
                        196
                    ],
                    "type": "Effect",
                    "effectName": "Movement 9"
                },
                {
                    "dmxRange": [
                        197,
                        217
                    ],
                    "type": "Effect",
                    "effectName": "Movement 10"
                },
                {
                    "dmxRange": [
                        218,
                        238
                    ],
                    "type": "Effect",
                    "effectName": "Movement 11"
                },
                {
                    "dmxRange": [
                        239,
                        255
                    ],
                    "type": "Effect",
                    "effectName": "Movement 12"
                }
            ]
        },
        "Movement Speed": {
            "defaultValue": 0,
            "capability": {
                "type": "PanTiltSpeed",
                "speedStart": "fast",
                "speedEnd": "slow"
            }
        }
    },
    "modes": [
        {
            "name": "8-channel",
            "shortName": "8ch",
            "channels": [
                "Pan",
                "Tilt",
                "Colors",
                "Gobo Wheel",
                "Shutter/Strobe",
                "Dimmer",
                "Moving Head Movement",
                "Movement Speed"
            ]
        }
    ]
}